{
	"id": "TUR_dummy01",
	"name": "Dummy Turret",
	"on_tank_position": "!transf;5.5;-5.5;0.0;0.0;0.0;0.0;9.0;9.0;1.0",
	"mass": 10.0,
	"shop_item": "!img;TankParts\\Turrets\\Dummy\\Images\\shop_img",
	"garage_item": "!img;TankParts\\Turrets\\Dummy\\Images\\garage_img",
	"weapons_shop": "!img;TankParts\\Turrets\\Dummy\\Images\\weapon_shop_img",
	"spritesheet": "!sprites;TankParts\\Turrets\\Dummy\\Images\\Sprites\\spritesheet_0",
	"light_weapon_slots": [
		"!wpnslt;2;!transf;0.95;0.4;0.0;0.0;0.0;0.0;1.0;1.5;1.0"
	],
	"heavy_weapon_slots": [
		"!wpnslt;1;!transf;1.35;0.4;0.0;0.0;0.0;0.0;1.0;1.0;1.0"
	]
}